README.md
setup.py
google/__init__.py
google/api/__init__.py
google/api/annotations_pb2.py
google/api/annotations_pb2_grpc.py
google/api/http_pb2.py
google/api/http_pb2_grpc.py
libopenstorage_openstorage.egg-info/PKG-INFO
libopenstorage_openstorage.egg-info/SOURCES.txt
libopenstorage_openstorage.egg-info/dependency_links.txt
libopenstorage_openstorage.egg-info/requires.txt
libopenstorage_openstorage.egg-info/top_level.txt
openstorage/__init__.py
openstorage/api_pb2.py
openstorage/api_pb2_grpc.py
openstorage/connector.py