Metadata-Version: 2.1
Name: libopenstorage-openstorage
Version: 0.42.24.1
Summary: OpenStorage SDK Python gRPC Client Library
Home-page: https://github.com/libopenstorage/openstorage-sdk-clients
Author: Portworx
Author-email: luis@portworx.com
License: UNKNOWN
Platform: UNKNOWN
Classifier: Programming Language :: Python :: 3
Classifier: License :: OSI Approved :: Apache Software License
Classifier: Operating System :: OS Independent
Requires-Python: >=3.0
